torch_archs/base/patches.py
torch_archs/base/attention/gqa.py
torch_archs/language/moe.py
torch_archs/tests/test_base/test_patches.py
torch_archs/vision/vit.py
torch_archs-0.1.2.dist-info/METADATA
torch_archs-0.1.2.dist-info/WHEEL
torch_archs-0.1.2.dist-info/top_level.txt
torch_archs-0.1.2.dist-info/RECORD
