Metadata-Version: 2.4
Name: torch-archs
Version: 0.1.2
Summary: PyTorch vision and language architectures.
Requires-Python: >=3.11
Requires-Dist: torch>=2.4
